wiver/__init__.py
wiver/_version.py
wiver/wiver_cython.c
wiver/wiver_cython.cp311-win_amd64.pyd
wiver/wiver_cython.pxd
wiver/wiver_cython.pyx
wiver/wiver_cython.pyxbld
wiver/wiver_python.py
wiver/tests/__init__.py
wiver/tests/test_wiver.py
wiver/tests/test_wiver_benchmark.py
wiver-1.14.0.dist-info/METADATA
wiver-1.14.0.dist-info/WHEEL
wiver-1.14.0.dist-info/top_level.txt
wiver-1.14.0.dist-info/RECORD
